{
    "format_version": "1.21.10",
    "minecraft:item": {
        "description": {
            "identifier": "fnaf:perspective"
        },
        "components": {
            "minecraft:max_stack_size": 1,
            "minecraft:icon": {
                "textures": {
                    "default": "camera_2"
                }
            },
            "minecraft:display_name": {
                "value": "Change Camera Perspective"
            },
            "minecraft:custom_components": [ "fnaf:switch" ]
        }
    }
}