{
    "format_version": "1.16.100",
    "minecraft:entity": {
        "description": {
            "identifier": "fnaf:balloon",
            "is_spawnable": false,
            "is_summonable": true
        },
        "components": {
            "minecraft:collision_box": {
                "height": 0,
                "width": 0
            },
            "minecraft:physics": {
                "has_collision": true,
                "has_gravity": false
            },
            "minecraft:pushable": {
                "is_pushable": false,
                "is_pushable_by_piston": false
            },
            "minecraft:damage_sensor": {
                "triggers": [ {
                    "cause": "all",
                    "deals_damage": false
                } ]
            },
            "minecraft:is_dyeable": {
                "interact_text": "dye"
            }
        }
    }
}